CHANGELOG.rst
CONTRIBUTING.rst
LICENSE-MIT.txt
MANIFEST.in
README.rst
TODO.rst
setup.py
autosign/__init__.py
autosign/config.py
autosign/exce.py
autosign/info.py
autosign/main.py
autosign.egg-info/PKG-INFO
autosign.egg-info/SOURCES.txt
autosign.egg-info/dependency_links.txt
autosign.egg-info/top_level.txt
autosign/parse/__init__.py
autosign/parse/autosign_options.py
autosign/parse/listsign_options.py
autosign/parse/parent_parser.py
autosign/parse/remsign_options.py
bin/autosign
bin/listsign
bin/remsign
tests/__init__.py
tests/helper.py
tests/test_checkFiles.py
tests/test_checkTemplate.py
tests/test_checkType.py
tests/test_getIndex.py
tests/test_isSign.py
tests/test_removeInter.py
tests/test_removeSign.py
tests/test_removeSignFile.py
tests/test_sign.py
tests/test_signFiles.py