Metadata-Version: 1.1
Name: autosign
Version: 1.1.0
Summary: Adds signature to your python files
Home-page: http://github.com/leosartaj/autosign
Author: Sartaj Singh
Author-email: singhsartaj94@gmail.com
License: MIT
Keywords: auto signature autosign
Platform: UNKNOWN
Classifier: Development Status :: 3 - Alpha
Classifier: License :: OSI Approved :: MIT License
Classifier: Environment :: Console
Classifier: Natural Language :: English
Classifier: Programming Language :: Python :: 2.7
